7_Setimo_Semestre/Logica/projeto2/decodificador_7seg.vhd
-- =====================================================================
-- Projeto: PR2 - Gerador de Sinais (DE10-Lite)
-- Disciplina: Logica Reconfiguravel - LR27CP-7CP
-- Alunos/RAs: TODO (nome - RA; um por linha)
-- Onda implementada: dente de serra / rampa crescente (wav 5)
-- Link do video: TODO
-- Valor de R (R-2R): TODO (recomendado 10k, 2R=20k)
-- =====================================================================
library ieee;
use ieee.std_logic_1164.all;
use ieee.numeric_std.all;

entity decodificador_7seg is
  port (
    valor : in  unsigned(3 downto 0);
    seg   : out std_logic_vector(6 downto 0)  -- ativo-baixo, seg(0)=a..seg(6)=g
  );
end entity;

architecture rtl of decodificador_7seg is
begin
  with valor select
    seg <= "1000000" when "0000",  -- 0
           "1111001" when "0001",  -- 1
           "0100100" when "0010",  -- 2
           "0110000" when "0011",  -- 3
           "0011001" when "0100",  -- 4
           "0010010" when "0101",  -- 5
           "0000010" when "0110",  -- 6
           "1111000" when "0111",  -- 7
           "0000000" when "1000",  -- 8
           "0010000" when "1001",  -- 9
           "1111111" when others;  -- apagado
end architecture;

7_Setimo_Semestre/Logica/projeto2/conformador_onda.vhd
-- =====================================================================
-- Projeto: PR2 - Gerador de Sinais (DE10-Lite)
-- Disciplina: Logica Reconfiguravel - LR27CP-7CP
-- Alunos/RAs: TODO (nome - RA; um por linha)
-- Onda implementada: dente de serra / rampa crescente (wav 5)
-- Link do video: TODO
-- Valor de R (R-2R): TODO (recomendado 10k, 2R=20k)
-- =====================================================================
library ieee;
use ieee.std_logic_1164.all;
use ieee.numeric_std.all;

entity conformador_onda is
  generic (N_BITS : natural := 8);
  port (
    fase_msb : in  unsigned(N_BITS-1 downto 0);
    sel_onda : in  std_logic;  -- '0'=quadrada, '1'=dente de serra
    dado     : out std_logic_vector(N_BITS-1 downto 0)
  );
end entity;

architecture rtl of conformador_onda is
  signal serra    : std_logic_vector(N_BITS-1 downto 0);
  signal quadrada : std_logic_vector(N_BITS-1 downto 0);
begin
  serra    <= std_logic_vector(fase_msb);
  quadrada <= (others => fase_msb(N_BITS-1));
  dado     <= serra when sel_onda = '1' else quadrada;
end architecture;

7_Setimo_Semestre/Logica/projeto2/acumulador_fase.vhd
-- =====================================================================
-- Projeto: PR2 - Gerador de Sinais (DE10-Lite)
-- Disciplina: Logica Reconfiguravel - LR27CP-7CP
-- Alunos/RAs: TODO (nome - RA; um por linha)
-- Onda implementada: dente de serra / rampa crescente (wav 5)
-- Link do video: TODO
-- Valor de R (R-2R): TODO (recomendado 10k, 2R=20k)
-- =====================================================================
library ieee;
use ieee.std_logic_1164.all;
use ieee.numeric_std.all;

entity acumulador_fase is
  generic (ACC_WIDTH : natural := 32);
  port (
    clk        : in  std_logic;
    rst        : in  std_logic;  -- reset sincrono, ativo-alto
    incremento : in  unsigned(ACC_WIDTH-1 downto 0);
    fase       : out unsigned(ACC_WIDTH-1 downto 0)
  );
end entity;

architecture rtl of acumulador_fase is
  signal acc : unsigned(ACC_WIDTH-1 downto 0) := (others => '0');
begin
  process(clk)
  begin
    if rising_edge(clk) then
      if rst = '1' then
        acc <= (others => '0');
      else
        acc <= acc + incremento;
      end if;
    end if;
  end process;
  fase <= acc;
end architecture;

7_Setimo_Semestre/Logica/projeto2/gerador_sinais.vhd
-- =====================================================================
-- Projeto: PR2 - Gerador de Sinais (DE10-Lite)
-- Disciplina: Logica Reconfiguravel - LR27CP-7CP
-- Alunos/RAs: TODO (nome - RA; um por linha)
-- Onda implementada: dente de serra / rampa crescente (wav 5)
-- Link do video: TODO
-- Valor de R (R-2R): TODO (recomendado 10k, 2R=20k)
-- =====================================================================
library ieee;
use ieee.std_logic_1164.all;
use ieee.numeric_std.all;
use work.gerador_pkg.all;

entity gerador_sinais is
  generic (
    CLK_HZ    : natural := 50_000_000;
    N_BITS    : natural := 8;
    ACC_WIDTH : natural := 32;
    FREQ1     : natural := 400;
    FREQ2     : natural := 800;
    WAV_NUM   : natural := 5
  );
  port (
    clk50 : in  std_logic;                              -- MAX10_CLK1_50
    key0  : in  std_logic;                              -- reset (ativo-baixo)
    sw0   : in  std_logic;                              -- '0'=freq1, '1'=freq2
    sw9   : in  std_logic;                              -- '0'=quadrada, '1'=serra
    gpio  : out std_logic_vector(N_BITS-1 downto 0);    -- GPIO[7:0] -> R-2R
    hex2  : out std_logic_vector(6 downto 0);           -- unidade da freq
    hex3  : out std_logic_vector(6 downto 0);           -- dezena da freq
    hex4  : out std_logic_vector(6 downto 0);           -- centena da freq
    hex5  : out std_logic_vector(6 downto 0)            -- numero da onda
  );
end entity;

architecture rtl of gerador_sinais is
  constant INC1 : unsigned(ACC_WIDTH-1 downto 0) := calc_incremento(FREQ1, CLK_HZ, ACC_WIDTH);
  constant INC2 : unsigned(ACC_WIDTH-1 downto 0) := calc_incremento(FREQ2, CLK_HZ, ACC_WIDTH);

  signal rst        : std_logic;
  signal incremento : unsigned(ACC_WIDTH-1 downto 0);
  signal fase       : unsigned(ACC_WIDTH-1 downto 0);
  signal fase_top   : unsigned(N_BITS-1 downto 0);

  signal d_cent, d_dez, d_uni, d_onda : unsigned(3 downto 0);
begin
  rst        <= not key0;
  incremento <= INC2 when sw0 = '1' else INC1;

  acc: acumulador_fase
    generic map (ACC_WIDTH => ACC_WIDTH)
    port map (clk => clk50, rst => rst, incremento => incremento, fase => fase);

  fase_top <= fase(ACC_WIDTH-1 downto ACC_WIDTH-N_BITS);

  conf: conformador_onda
    generic map (N_BITS => N_BITS)
    port map (fase_msb => fase_top, sel_onda => sw9, dado => gpio);

  -- Digitos da frequencia ativa (constantes mux por sw0)
  d_cent <= digito_freq(FREQ2, 2) when sw0 = '1' else digito_freq(FREQ1, 2);
  d_dez  <= digito_freq(FREQ2, 1) when sw0 = '1' else digito_freq(FREQ1, 1);
  d_uni  <= digito_freq(FREQ2, 0) when sw0 = '1' else digito_freq(FREQ1, 0);
  d_onda <= to_unsigned(WAV_NUM, 4) when sw9 = '1' else to_unsigned(0, 4);

  dec_h4: decodificador_7seg port map (valor => d_cent, seg => hex4);
  dec_h3: decodificador_7seg port map (valor => d_dez,  seg => hex3);
  dec_h2: decodificador_7seg port map (valor => d_uni,  seg => hex2);
  dec_h5: decodificador_7seg port map (valor => d_onda, seg => hex5);
end architecture;

7_Setimo_Semestre/Logica/projeto2/gerador_sinais_tb.vhd
-- =====================================================================
-- Projeto: PR2 - Gerador de Sinais (DE10-Lite)
-- Disciplina: Logica Reconfiguravel - LR27CP-7CP
-- Alunos/RAs: TODO (nome - RA; um por linha)
-- Onda implementada: dente de serra / rampa crescente (wav 5)
-- Link do video: TODO
-- Valor de R (R-2R): TODO (recomendado 10k, 2R=20k)
-- =====================================================================
library ieee;
use ieee.std_logic_1164.all;
use ieee.numeric_std.all;
use std.env.all;

entity gerador_sinais_tb is
end entity;

architecture sim of gerador_sinais_tb is
  signal clk50 : std_logic := '0';
  signal key0  : std_logic := '1';
  signal sw0   : std_logic := '0';
  signal sw9   : std_logic := '0';
  signal gpio  : std_logic_vector(7 downto 0);
  signal hex2, hex3, hex4, hex5 : std_logic_vector(6 downto 0);
begin
  dut: entity work.gerador_sinais
    generic map (CLK_HZ => 800, N_BITS => 8, ACC_WIDTH => 32,
                 FREQ1 => 100, FREQ2 => 200, WAV_NUM => 5)
    port map (clk50 => clk50, key0 => key0, sw0 => sw0, sw9 => sw9,
              gpio => gpio, hex2 => hex2, hex3 => hex3, hex4 => hex4, hex5 => hex5);

  clk50 <= not clk50 after 10 ns;  -- 50 MHz simbolico

  stimulus: process
  begin
    -- ===== DENTE DE SERRA: rampa 0,32,64,...,224, wrap =====
    sw9 <= '1'; sw0 <= '0';
    key0 <= '0'; wait until rising_edge(clk50); wait for 1 ns;  -- reset -> fase=0
    key0 <= '1';
    assert gpio = std_logic_vector(to_unsigned(0, 8)) report "serra[0]" severity error;
    for k in 1 to 8 loop
      wait until rising_edge(clk50); wait for 1 ns;
      assert gpio = std_logic_vector(to_unsigned((k*32) mod 256, 8))
        report "serra passo errado" severity error;
    end loop;

    -- ===== QUADRADA: 4x 0x00, depois 4x 0xFF =====
    sw9 <= '0';
    key0 <= '0'; wait until rising_edge(clk50); wait for 1 ns;  -- reset -> fase=0
    key0 <= '1';
    for k in 0 to 7 loop
      if k > 0 then
        wait until rising_edge(clk50); wait for 1 ns;
      end if;
      if k < 4 then
        assert gpio = "00000000" report "quadrada nivel baixo" severity error;
      else
        assert gpio = "11111111" report "quadrada nivel alto" severity error;
      end if;
    end loop;

    -- ===== HEX5: formato da onda =====
    sw9 <= '1'; wait for 1 ns;
    assert hex5 = "0010010" report "HEX5 deveria mostrar 5 (serra)" severity error;
    sw9 <= '0'; wait for 1 ns;
    assert hex5 = "1000000" report "HEX5 deveria mostrar 0 (quadrada)" severity error;

    -- ===== HEX4/3/2: valor da frequencia =====
    sw0 <= '0'; wait for 1 ns;  -- freq1 = 100
    assert hex4 = "1111001" report "HEX4 freq1 (centena=1)" severity error;
    assert hex3 = "1000000" report "HEX3 freq1 (dezena=0)" severity error;
    assert hex2 = "1000000" report "HEX2 freq1 (unidade=0)" severity error;
    sw0 <= '1'; wait for 1 ns;  -- freq2 = 200
    assert hex4 = "0100100" report "HEX4 freq2 (centena=2)" severity error;

    report "gerador_sinais_tb: sucesso" severity note;
    finish;
  end process;
end architecture;

7_Setimo_Semestre/Logica/projeto2/wave.vcd
$date
  Tue Jun 30 12:11:33 2026
$end
$version
  GHDL v0
$end
$timescale
  1 fs
$end
$scope module standard $end
$upscope $end
$scope module textio $end
$upscope $end
$scope module std_logic_1164 $end
$upscope $end
$scope module numeric_std $end
$upscope $end
$scope module env $end
$upscope $end
$scope module math_real $end
$upscope $end
$scope module gerador_pkg $end
$upscope $end
$scope module gerador_sinais_tb $end
$var reg 1 ! clk50 $end
$var reg 1 " key0 $end
$var reg 1 # sw0 $end
$var reg 1 $ sw9 $end
$var reg 8 % gpio[7:0] $end
$var reg 7 & hex2[6:0] $end
$var reg 7 ' hex3[6:0] $end
$var reg 7 ( hex4[6:0] $end
$var reg 7 ) hex5[6:0] $end
$scope module dut $end
$var reg 1 * clk50 $end
$var reg 1 + key0 $end
$var reg 1 , sw0 $end
$var reg 1 - sw9 $end
$var reg 8 . gpio[7:0] $end
$var reg 7 / hex2[6:0] $end
$var reg 7 0 hex3[6:0] $end
$var reg 7 1 hex4[6:0] $end
$var reg 7 2 hex5[6:0] $end
$var reg 1 3 rst $end
$var reg 32 4 incremento[31:0] $end
$var reg 32 5 fase[31:0] $end
$var reg 8 6 fase_top[7:0] $end
$var reg 4 7 d_cent[3:0] $end
$var reg 4 8 d_dez[3:0] $end
$var reg 4 9 d_uni[3:0] $end
$var reg 4 : d_onda[3:0] $end
$scope module acc $end
$var reg 1 ; clk $end
$var reg 1 < rst $end
$var reg 32 = incremento[31:0] $end
$var reg 32 > fase[31:0] $end
$var reg 32 ? acc[31:0] $end
$upscope $end
$scope module conf $end
$var reg 8 @ fase_msb[7:0] $end
$var reg 1 A sel_onda $end
$var reg 8 B dado[7:0] $end
$var reg 8 C serra[7:0] $end
$var reg 8 D quadrada[7:0] $end
$upscope $end
$scope module dec_h4 $end
$var reg 4 E valor[3:0] $end
$var reg 7 F seg[6:0] $end
$upscope $end
$scope module dec_h3 $end
$var reg 4 G valor[3:0] $end
$var reg 7 H seg[6:0] $end
$upscope $end
$scope module dec_h2 $end
$var reg 4 I valor[3:0] $end
$var reg 7 J seg[6:0] $end
$upscope $end
$scope module dec_h5 $end
$var reg 4 K valor[3:0] $end
$var reg 7 L seg[6:0] $end
$upscope $end
$upscope $end
$upscope $end
$enddefinitions $end
#0
0!
0"
0#
1$
b00000000 %
b1000000 &
b1000000 '
b1111001 (
b0010010 )
0*
0+
0,
1-
b00000000 .
b1000000 /
b1000000 0
b1111001 1
b0010010 2
13
b00100000000000000000000000000000 4
b00000000000000000000000000000000 5
b00000000 6
b0001 7
b0000 8
b0000 9
b0101 :
0;
1<
b00100000000000000000000000000000 =
b00000000000000000000000000000000 >
b00000000000000000000000000000000 ?
b00000000 @
1A
b00000000 B
b00000000 C
b00000000 D
b0001 E
b1111001 F
b0000 G
b1000000 H
b0000 I
b1000000 J
b0101 K
b0010010 L
#10000000
1!
1*
1;
#11000000
1"
1+
03
0<
#20000000
0!
0*
0;
#30000000
1!
b00100000 %
1*
b00100000 .
b00100000000000000000000000000000 5
b00100000 6
1;
b00100000000000000000000000000000 >
b00100000000000000000000000000000 ?
b00100000 @
b00100000 B
b00100000 C
#40000000
0!
0*
0;
#50000000
1!
b01000000 %
1*
b01000000 .
b01000000000000000000000000000000 5
b01000000 6
1;
b01000000000000000000000000000000 >
b01000000000000000000000000000000 ?
b01000000 @
b01000000 B
b01000000 C
#60000000
0!
0*
0;
#70000000
1!
b01100000 %
1*
b01100000 .
b01100000000000000000000000000000 5
b01100000 6
1;
b01100000000000000000000000000000 >
b01100000000000000000000000000000 ?
b01100000 @
b01100000 B
b01100000 C
#80000000
0!
0*
0;
#90000000
1!
b10000000 %
1*
b10000000 .
b10000000000000000000000000000000 5
b10000000 6
1;
b10000000000000000000000000000000 >
b10000000000000000000000000000000 ?
b10000000 @
b10000000 B
b10000000 C
b11111111 D
#100000000
0!
0*
0;
#110000000
1!
b10100000 %
1*
b10100000 .
b10100000000000000000000000000000 5
b10100000 6
1;
b10100000000000000000000000000000 >
b10100000000000000000000000000000 ?
b10100000 @
b10100000 B
b10100000 C
#120000000
0!
0*
0;
#130000000
1!
b11000000 %
1*
b11000000 .
b11000000000000000000000000000000 5
b11000000 6
1;
b11000000000000000000000000000000 >
b11000000000000000000000000000000 ?
b11000000 @
b11000000 B
b11000000 C
#140000000
0!
0*
0;
#150000000
1!
b11100000 %
1*
b11100000 .
b11100000000000000000000000000000 5
b11100000 6
1;
b11100000000000000000000000000000 >
b11100000000000000000000000000000 ?
b11100000 @
b11100000 B
b11100000 C
#160000000
0!
0*
0;
#170000000
1!
b00000000 %
1*
b00000000 .
b00000000000000000000000000000000 5
b00000000 6
1;
b00000000000000000000000000000000 >
b00000000000000000000000000000000 ?
b00000000 @
b00000000 B
b00000000 C
b00000000 D
#171000000
0"
0$
b1000000 )
0+
0-
b1000000 2
13
b0000 :
1<
0A
b0000 K
b1000000 L
#180000000
0!
0*
0;
#190000000
1!
1*
1;
#191000000
1"
1+
03
0<
#200000000
0!
0*
0;
#210000000
1!
1*
b00100000000000000000000000000000 5
b00100000 6
1;
b00100000000000000000000000000000 >
b00100000000000000000000000000000 ?
b00100000 @
b00100000 C
#220000000
0!
0*
0;
#230000000
1!
1*
b01000000000000000000000000000000 5
b01000000 6
1;
b01000000000000000000000000000000 >
b01000000000000000000000000000000 ?
b01000000 @
b01000000 C
#240000000
0!
0*
0;
#250000000
1!
1*
b01100000000000000000000000000000 5
b01100000 6
1;
b01100000000000000000000000000000 >
b01100000000000000000000000000000 ?
b01100000 @
b01100000 C
#260000000
0!
0*
0;
#270000000
1!
b11111111 %
1*
b11111111 .
b10000000000000000000000000000000 5
b10000000 6
1;
b10000000000000000000000000000000 >
b10000000000000000000000000000000 ?
b10000000 @
b11111111 B
b10000000 C
b11111111 D
#280000000
0!
0*
0;
#290000000
1!
1*
b10100000000000000000000000000000 5
b10100000 6
1;
b10100000000000000000000000000000 >
b10100000000000000000000000000000 ?
b10100000 @
b10100000 C
#300000000
0!
0*
0;
#310000000
1!
1*
b11000000000000000000000000000000 5
b11000000 6
1;
b11000000000000000000000000000000 >
b11000000000000000000000000000000 ?
b11000000 @
b11000000 C
#320000000
0!
0*
0;
#330000000
1!
1*
b11100000000000000000000000000000 5
b11100000 6
1;
b11100000000000000000000000000000 >
b11100000000000000000000000000000 ?
b11100000 @
b11100000 C
#331000000
1$
b11100000 %
b0010010 )
1-
b11100000 .
b0010010 2
b0101 :
1A
b11100000 B
b0101 K
b0010010 L
#332000000
0$
b11111111 %
b1000000 )
0-
b11111111 .
b1000000 2
b0000 :
0A
b11111111 B
b0000 K
b1000000 L
#334000000
1#
b0100100 (
1,
b0100100 1
b01000000000000000000000000000000 4
b0010 7
b01000000000000000000000000000000 =
b0010 E
b0100100 F
